vouch/__init__.py
vouch/audio.py
vouch/auditor.py
vouch/cli.py
vouch/keys.py
vouch/kms.py
vouch/seal.py
vouch/signer.py
vouch/verifier.py
vouch/integrations/google.py
vouch/integrations/n8n.py
vouch/integrations/autogen/__init__.py
vouch/integrations/autogen/tool.py
vouch/integrations/autogpt/__init__.py
vouch/integrations/autogpt/commands.py
vouch/integrations/crewai/__init__.py
vouch/integrations/crewai/tool.py
vouch/integrations/langchain/__init__.py
vouch/integrations/langchain/tool.py
vouch/integrations/langchain/tools.py
vouch/integrations/mcp/__init__.py
vouch/integrations/mcp/server.py
vouch/integrations/vertex_ai/__init__.py
vouch/integrations/vertex_ai/tool.py
vouch_protocol-1.1.0.dist-info/licenses/LICENSE
vouch_protocol-1.1.0.dist-info/METADATA
vouch_protocol-1.1.0.dist-info/WHEEL
vouch_protocol-1.1.0.dist-info/entry_points.txt
vouch_protocol-1.1.0.dist-info/top_level.txt
vouch_protocol-1.1.0.dist-info/RECORD
