Metadata-Version: 2.4
Name: vouch-protocol
Version: 1.1.0
Summary: The Identity & Reputation Standard for AI Agents
Author-email: Vouch Protocol Contributors <hello@vouch-protocol.org>
License:                     GNU AFFERO GENERAL PUBLIC LICENSE
Project-URL: Homepage, https://github.com/vouch-protocol/vouch
Project-URL: Bug Tracker, https://github.com/vouch-protocol/vouch/issues
Classifier: Development Status :: 4 - Beta
Classifier: Intended Audience :: Developers
Classifier: License :: OSI Approved :: GNU Affero General Public License v3
Classifier: Programming Language :: Python :: 3
Requires-Python: >=3.9
License-File: LICENSE
Requires-Dist: pynacl
Requires-Dist: cryptography
Requires-Dist: pydantic
Requires-Dist: httpx
Requires-Dist: fastapi
Requires-Dist: uvicorn
Requires-Dist: redis>=5.0.0
Provides-Extra: langchain
Requires-Dist: langchain; extra == "langchain"
Provides-Extra: mcp
Requires-Dist: mcp; extra == "mcp"
Provides-Extra: vertex
Requires-Dist: google-cloud-aiplatform; extra == "vertex"
Provides-Extra: crewai
Requires-Dist: crewai; extra == "crewai"
Provides-Extra: autogen
Requires-Dist: pyautogen; extra == "autogen"
Dynamic: license-file
